axanexa_moncli/__init__.py
axanexa_moncli/config.py
axanexa_moncli/enums.py
axanexa_moncli/error.py
axanexa_moncli/models.py
axanexa_moncli/types.py
axanexa_moncli/api_v1/__init__.py
axanexa_moncli/api_v1/boards.py
axanexa_moncli/api_v1/constants.py
axanexa_moncli/api_v1/pulses.py
axanexa_moncli/api_v1/requests.py
axanexa_moncli/api_v1/tags.py
axanexa_moncli/api_v1/updates.py
axanexa_moncli/api_v1/users.py
axanexa_moncli/api_v2/__init__.py
axanexa_moncli/api_v2/constants.py
axanexa_moncli/api_v2/exceptions.py
axanexa_moncli/api_v2/graphql.py
axanexa_moncli/api_v2/handlers.py
axanexa_moncli/api_v2/requests.py
axanexa_moncli/column_value/__init__.py
axanexa_moncli/column_value/base.py
axanexa_moncli/column_value/complex.py
axanexa_moncli/column_value/constants.py
axanexa_moncli/column_value/objects.py
axanexa_moncli/column_value/readonly.py
axanexa_moncli/column_value/simple.py
axanexa_moncli/entities/__init__.py
axanexa_moncli/entities/asset.py
axanexa_moncli/entities/base.py
axanexa_moncli/entities/board.py
axanexa_moncli/entities/client.py
axanexa_moncli/entities/column.py
axanexa_moncli/entities/group.py
axanexa_moncli/entities/item.py
axanexa_moncli/entities/objects.py
axanexa_moncli/entities/update.py
axanexa_moncli/entities/user.py
axanexa_moncli-3.0.1.dist-info/LICENSE
axanexa_moncli-3.0.1.dist-info/METADATA
axanexa_moncli-3.0.1.dist-info/WHEEL
axanexa_moncli-3.0.1.dist-info/top_level.txt
axanexa_moncli-3.0.1.dist-info/RECORD
